acCRISPR/CS_FS_guide.py
acCRISPR/CS_corr_lib.py
acCRISPR/FS_gene_calc.py
acCRISPR/FS_to_p_val.py
acCRISPR/__init__.py
acCRISPR/ac_CRISPR.py
acCRISPR/run_acCRISPR.py
acCRISPR-1.0.0.dist-info/LICENSE
acCRISPR-1.0.0.dist-info/METADATA
acCRISPR-1.0.0.dist-info/WHEEL
acCRISPR-1.0.0.dist-info/top_level.txt
acCRISPR-1.0.0.dist-info/RECORD
