Metadata-Version: 2.1
Name: acCRISPR
Version: 1.0.0
Summary: Identification of essential genes by sgRNA activity-correction from CRISPR screening data
Author-email: Varun Trivedi <vtriv002@ucr.edu>
Project-URL: Homepage, https://github.com/ianwheeldon/acCRISPR
Classifier: Programming Language :: Python :: 3
Classifier: License :: OSI Approved :: MIT License
Classifier: Operating System :: OS Independent
Classifier: Intended Audience :: Science/Research
Classifier: Natural Language :: English
Classifier: Topic :: Scientific/Engineering :: Bio-Informatics
Requires-Python: >=3.6
License-File: LICENSE
Requires-Dist: numpy (>=1.18.1)
Requires-Dist: matplotlib (>=3.4.2)
